caller/__init__.py
caller/caller.py
simc_autobahn/__init__.py
simc_autobahn/models.py
simc_autobahn/my_logger.py
simc_autobahn/py_version_check.py
simc_autobahn/simc_permutations.py
simc_autobahn-1.0.3.dist-info/DESCRIPTION.rst
simc_autobahn-1.0.3.dist-info/METADATA
simc_autobahn-1.0.3.dist-info/RECORD
simc_autobahn-1.0.3.dist-info/WHEEL
simc_autobahn-1.0.3.dist-info/metadata.json
simc_autobahn-1.0.3.dist-info/top_level.txt
subscriber/__init__.py
subscriber/subscriber.py
worker/__init__.py
worker/worker.py
