Metadata-Version: 2.0
Name: simc-autobahn
Version: 1.0.3
Summary: A SimC microservice build with Crossbar.io/ Autobahn
Home-page: https://gitlab.com/simc/simc-autobahn
Author: endymonium
Author-email: endymonium@gmail.com
License: GNU GPLv3 
Platform: UNKNOWN
Requires-Dist: autobahn
Requires-Dist: bs4
Requires-Dist: docopt
Requires-Dist: peewee
Requires-Dist: requests
Requires-Dist: yattag
